prog/__init__.py
prog/cli.py
prog/commands.py
prog/parse.py
prog/util.py
prog/assets/prog.json
prog/assets/prog.yml
prog_0.1.2-0.1.2.dist-info/LICENSE
prog_0.1.2-0.1.2.dist-info/METADATA
prog_0.1.2-0.1.2.dist-info/WHEEL
prog_0.1.2-0.1.2.dist-info/entry_points.txt
prog_0.1.2-0.1.2.dist-info/top_level.txt
prog_0.1.2-0.1.2.dist-info/RECORD
