Metadata-Version: 2.1
Name: prog-0.1.2
Version: 0.1.2
Summary: A tool for centralizing scripted shell commands via a configurable JSON or YAML file
Home-page: https://github.com/bdreece/prog
Author: Brian Reece
Author-email: bdreece@mtu.edu
License: UNKNOWN
Platform: UNKNOWN
Requires-Python: >=3.6
Requires-Dist: Click
Requires-Dist: pyyaml
